{
    "key": "group_651a97b6a81cf",
    "title": "Template: Vacature",
    "fields": [
        {
            "key": "field_651a97b760e93",
            "label": "Titel boven de vacatures",
            "name": "tpl_vacancies_title",
            "aria-label": "",
            "type": "text",
            "instructions": "",
            "required": 0,
            "conditional_logic": 0,
            "wrapper": {
                "width": "",
                "class": "",
                "id": ""
            },
            "wpml_cf_preferences": 0,
            "default_value": "",
            "maxlength": "",
            "placeholder": "",
            "prepend": "",
            "append": ""
        },
        {
            "key": "field_651a97e760e94",
            "label": "Tekst",
            "name": "tpl_vacancies_text",
            "aria-label": "",
            "type": "wysiwyg",
            "instructions": "",
            "required": 0,
            "conditional_logic": 0,
            "wrapper": {
                "width": "",
                "class": "",
                "id": ""
            },
            "wpml_cf_preferences": 0,
            "default_value": "",
            "tabs": "all",
            "toolbar": "basic",
            "media_upload": 0,
            "delay": 0
        }
    ],
    "location": [
        [
            {
                "param": "page_template",
                "operator": "==",
                "value": "page-templates\/vacancies-small-header.php"
            }
        ],
        [
            {
                "param": "page_template",
                "operator": "==",
                "value": "page-templates\/vacancies.php"
            }
        ]
    ],
    "menu_order": 0,
    "position": "normal",
    "style": "default",
    "label_placement": "top",
    "instruction_placement": "label",
    "hide_on_screen": "",
    "active": true,
    "description": "",
    "show_in_rest": 0,
    "acfml_field_group_mode": "translation",
    "modified": 1696241826
}
